climoji/__init__.py
climoji/__main__.py
climoji/application/__init__.py
climoji/application/_finder.py
climoji/domain/__init__.py
climoji/domain/exception.py
climoji/domain/model.py
climoji/infrastructure/__init__.py
climoji/infrastructure/_command.py
climoji/infrastructure/container.py
climoji/infrastructure/_file_repository/__init__.py
climoji/infrastructure/_file_repository/_emoji_list.py
climoji/infrastructure/_file_repository/_emoji_repository.py
test/__init__.py
test/acceptance/__init__.py
test/acceptance/environment.py
climoji-3.0.0.dist-info/LICENSE
climoji-3.0.0.dist-info/METADATA
climoji-3.0.0.dist-info/WHEEL
climoji-3.0.0.dist-info/entry_points.txt
climoji-3.0.0.dist-info/top_level.txt
climoji-3.0.0.dist-info/RECORD
