Metadata-Version: 2.1
Name: climoji
Version: 3.0.0
Summary: A cli emoji finder
Home-page: https://github.com/psincraian/climoji
Author: Petru Rares Sincraian
Author-email: psincraian@gmail.com
License: MIT
Keywords: emoji cli finder
Platform: UNKNOWN
Requires-Dist: click (<7,>=6.7)
Requires-Dist: editdistance (<1.0)
